organizations/__init__.py
organizations/abstract.py
organizations/admin.py
organizations/app_settings.py
organizations/apps.py
organizations/base.py
organizations/base_admin.py
organizations/exceptions.py
organizations/fields.py
organizations/forms.py
organizations/managers.py
organizations/models.py
organizations/signals.py
organizations/urls.py
organizations/utils.py
organizations/backends/__init__.py
organizations/backends/defaults.py
organizations/backends/forms.py
organizations/backends/modeled.py
organizations/migrations/0001_initial.py
organizations/migrations/0002_model_update.py
organizations/migrations/0003_field_fix_and_editable.py
organizations/migrations/0004_organizationinvitation.py
organizations/migrations/0005_alter_organization_users_and_more.py
organizations/migrations/0006_alter_organization_slug.py
organizations/migrations/__init__.py
organizations/templates/organizations_base.html
organizations/templates/organizations/invitation_join.html
organizations/templates/organizations/login.html
organizations/templates/organizations/organization_confirm_delete.html
organizations/templates/organizations/organization_detail.html
organizations/templates/organizations/organization_form.html
organizations/templates/organizations/organization_list.html
organizations/templates/organizations/organization_users.html
organizations/templates/organizations/organizationuser_confirm_delete.html
organizations/templates/organizations/organizationuser_detail.html
organizations/templates/organizations/organizationuser_form.html
organizations/templates/organizations/organizationuser_list.html
organizations/templates/organizations/organizationuser_remind.html
organizations/templates/organizations/register_form.html
organizations/templates/organizations/register_success.html
organizations/templates/organizations/email/activation_body.html
organizations/templates/organizations/email/activation_subject.txt
organizations/templates/organizations/email/invitation_body.html
django_organizations-2.3.1.dist-info/AUTHORS.rst
django_organizations-2.3.1.dist-info/LICENSE
django_organizations-2.3.1.dist-info/METADATA
django_organizations-2.3.1.dist-info/WHEEL
django_organizations-2.3.1.dist-info/top_level.txt
django_organizations-2.3.1.dist-info/RECORD
