Metadata-Version: 2.1
Name: django-organizations
Version: 2.3.1
Summary: Group accounts for Django
Home-page: https://github.com/bennylope/django-organizations/
Author: Ben Lopatin
Author-email: ben@benlopatin.com
License: BSD License
Platform: OS Independent
Classifier: Framework :: Django
Classifier: Environment :: Web Environment
Classifier: Intended Audience :: Developers
Classifier: License :: OSI Approved :: BSD License
Classifier: Operating System :: OS Independent
Classifier: Programming Language :: Python
Classifier: Programming Language :: Python :: 3.8
Classifier: Programming Language :: Python :: 3.9
Classifier: Programming Language :: Python :: 3.10
Classifier: Programming Language :: Python :: 3.11
Classifier: Programming Language :: Python :: Implementation :: CPython
Classifier: Development Status :: 5 - Production/Stable
Requires-Python: >=3.8
License-File: LICENSE
License-File: AUTHORS.rst
Requires-Dist: Django>=3.2.0
Requires-Dist: django-extensions>=2.0.8
